aspring/__init__.py
aspring/main.py
aspring/step_01_preprocess.py
aspring/step_02_hmm_maker.py
aspring/step_03_hmm_aligner.py
aspring/step_04_gettable.py
aspring/step_05_filter.py
aspring/step_06_stats.py
aspring/step_07_reformat.py
aspring/step_08_ASRUs.py
aspring/step_09_clean.py
aspring/step_10_struct.py
aspring/R_script/.Rprofile
aspring/R_script/renv.lock
aspring/R_script/step_06_getStats.R
aspring/R_script/renv/.gitignore
aspring/R_script/renv/activate.R
aspring/R_script/renv/settings.dcf
aspring-1.3.1.dist-info/LICENSE.txt
aspring-1.3.1.dist-info/METADATA
aspring-1.3.1.dist-info/WHEEL
aspring-1.3.1.dist-info/entry_points.txt
aspring-1.3.1.dist-info/top_level.txt
aspring-1.3.1.dist-info/RECORD
