Metadata-Version: 2.1
Name: aspring
Version: 1.3.1
Summary: Alternatively Spliced Pseudo Repeat IN-Gene
Home-page: https://github.com/PhyloSofS-Team/aspring
Author: Antoine Szatkownik, Diego Javier Zea, Hugues Richard & Elodie Laine
Author-email: diegozea@gmail.com
License: MIT
Project-URL: Documentation, https://aspring.readthedocs.io/en/latest/
Project-URL: Source, https://github.com/PhyloSofS-Team/aspring
Project-URL: Changelog, https://github.com/PhyloSofS-Team/aspring/changelog.html
Project-URL: Tracker, https://github.com/PhyloSofS-Team/aspring/issues
Platform: Linux
Platform: Mac
Classifier: Development Status :: 4 - Beta
Classifier: Intended Audience :: Science/Research
Classifier: License :: OSI Approved :: MIT License
Classifier: Natural Language :: English
Classifier: Programming Language :: Python :: 3
Requires-Python: <3.12,>=3.7
License-File: LICENSE.txt
Requires-Dist: numpy (<1.30,>=1.12.0)
Requires-Dist: pandas (<1.6,>=0.21.0)
Requires-Dist: networkx (<2.9,>=2.3.0)
Requires-Dist: requests (<2.27,>=2.25)
Requires-Dist: biomart (<0.10,>=0.9.2)
Requires-Dist: importlib-metadata ; python_version < "3.8"
Provides-Extra: docs
Requires-Dist: sphinx-argparse ; extra == 'docs'
Provides-Extra: testing
Requires-Dist: setuptools ; extra == 'testing'
Requires-Dist: pytest ; extra == 'testing'
Requires-Dist: pytest-cov ; extra == 'testing'
